unit_converter_python/__init__.py
unit_converter_python/distance/__init__.py
unit_converter_python/distance/centimeter_conversion_to.py
unit_converter_python/distance/fathom_conversion_to.py
unit_converter_python/distance/feet_conversion_to.py
unit_converter_python/distance/inch_conversion_to.py
unit_converter_python/distance/kilometer_conversion_to.py
unit_converter_python/distance/meter_conversion_to.py
unit_converter_python/distance/mile_conversion_to.py
unit_converter_python/distance/yard_conversion_to.py
unit_converter_python/power/__init__.py
unit_converter_python/power/hp_conversion_to.py
unit_converter_python/power/kw_conversion_to.py
unit_converter_python/power/mhp_conversion_to.py
unit_converter_python/power/w_conversion_to.py
unit_converter_python/pressure/__init__.py
unit_converter_python/pressure/atm_conversion_to.py
unit_converter_python/pressure/bar_conversion_to.py
unit_converter_python/pressure/kgfm_conversion_to.py
unit_converter_python/pressure/pascal_convertion_to.py
unit_converter_python/pressure/psi_conversion_to.py
unit_converter_python/temperature/__init__.py
unit_converter_python/temperature/celsius_conversion_to.py
unit_converter_python/temperature/fahrenheit_conversion_to.py
unit_converter_python/temperature/kelvin_conversion_to.py
unit_converter_python/torque/__init__.py
unit_converter_python/torque/kgfm_conversion_to.py
unit_converter_python/torque/lbfft_conversion_to.py
unit_converter_python/torque/lbfin_conversion_to.py
unit_converter_python/torque/nm_conversion_to.py
unit_converter_python/weight/__init__.py
unit_converter_python/weight/gram_conversion_to.py
unit_converter_python/weight/kilogram_conversion_to.py
unit_converter_python/weight/ounce_conversion_to.py
unit_converter_python/weight/pound_conversion_to.py
unit_converter_python-0.0.2.dist-info/LICENSE
unit_converter_python-0.0.2.dist-info/METADATA
unit_converter_python-0.0.2.dist-info/WHEEL
unit_converter_python-0.0.2.dist-info/top_level.txt
unit_converter_python-0.0.2.dist-info/RECORD
