Metadata-Version: 2.1
Name: unit_converter_python
Version: 0.0.2
Summary: This project is a simple unit converter.
Home-page: https://github.com/Danieltandrade/Unit-Converter
Author: Daniel Torres de Andrade
Author-email: danieltorresandrade@gmail.com
License: MIT License
Keywords: unit converter,unit-converter,unit_converter
Classifier: Development Status :: 5 - Production/Stable
Classifier: Intended Audience :: Developers
Classifier: Intended Audience :: End Users/Desktop
Classifier: Intended Audience :: Science/Research
Classifier: Natural Language :: English
Classifier: License :: OSI Approved :: MIT License
Classifier: Programming Language :: Python
Classifier: Programming Language :: Python :: 3.8
Classifier: Programming Language :: Python :: 3.9
Classifier: Programming Language :: Python :: 3.10
Classifier: Programming Language :: Python :: 3.11
Classifier: Programming Language :: Python :: 3.12
Classifier: Topic :: Scientific/Engineering
Classifier: Topic :: Software Development
Requires-Python: >=3.8
License-File: LICENSE
